{
    "KPlugin": {
        "Authors": [
            {
                "Email": "itay.avra@gmail.com"
            }
        ],
        "Category": "System Information",
        "Description": "Monitor battery levels of all connected devices",
        "Icon": "/icons/battery-monitor.png",
        "Id": "com.github.itayavra.batterywatch",
        "Name": "BatteryWatch",
        "Version": "0.1.8",
        "Website": "https://github.com/itayavra/batterywatch"
    },
    "KPackageStructure": "Plasma/Applet",
    "X-Plasma-API-Minimum-Version": "6.0"
}